cis_bench/__init__.py
cis_bench/__main__.py
cis_bench/config.py
cis_bench/exceptions.py
cis_bench/catalog/__init__.py
cis_bench/catalog/database.py
cis_bench/catalog/downloader.py
cis_bench/catalog/models.py
cis_bench/catalog/parser.py
cis_bench/catalog/scraper.py
cis_bench/catalog/search.py
cis_bench/cli/__init__.py
cis_bench/cli/app.py
cis_bench/cli/commands/__init__.py
cis_bench/cli/commands/auth.py
cis_bench/cli/commands/catalog.py
cis_bench/cli/commands/download.py
cis_bench/cli/commands/export.py
cis_bench/cli/commands/get.py
cis_bench/cli/commands/info.py
cis_bench/cli/commands/list_cmd.py
cis_bench/cli/commands/search.py
cis_bench/cli/helpers/__init__.py
cis_bench/cli/helpers/download_helper.py
cis_bench/cli/helpers/output.py
cis_bench/exporters/__init__.py
cis_bench/exporters/base.py
cis_bench/exporters/csv_exporter.py
cis_bench/exporters/json_exporter.py
cis_bench/exporters/mapping_engine.py
cis_bench/exporters/markdown_exporter.py
cis_bench/exporters/xccdf_unified_exporter.py
cis_bench/exporters/yaml_exporter.py
cis_bench/exporters/configs/base.yaml
cis_bench/exporters/configs/styles/cis.yaml
cis_bench/exporters/configs/styles/disa.yaml
cis_bench/fetcher/__init__.py
cis_bench/fetcher/auth.py
cis_bench/fetcher/workbench.py
cis_bench/fetcher/strategies/__init__.py
cis_bench/fetcher/strategies/base.py
cis_bench/fetcher/strategies/detector.py
cis_bench/fetcher/strategies/v1_current.py
cis_bench/models/__init__.py
cis_bench/models/benchmark.py
cis_bench/models/cis_controls_official.py
cis_bench/models/enhanced_metadata.py
cis_bench/models/xccdf/__init__.py
cis_bench/models/xccdf/xccdf_1_2.py
cis_bench/models/xccdf/xml.py
cis_bench/models/xccdf_v1_1/__init__.py
cis_bench/models/xccdf_v1_1/dc.py
cis_bench/models/xccdf_v1_1/xccdf_1_1_4.py
cis_bench/models/xccdf_v1_1/xml.py
cis_bench/utils/__init__.py
cis_bench/utils/cci_lookup.py
cis_bench/utils/field_transformers.py
cis_bench/utils/html_parser.py
cis_bench/utils/logging_config.py
cis_bench/utils/parsers.py
cis_bench-0.5.0.dist-info/licenses/LICENSE.md
cis_bench-0.5.0.dist-info/licenses/NOTICE.md
cis_bench-0.5.0.dist-info/METADATA
cis_bench-0.5.0.dist-info/WHEEL
cis_bench-0.5.0.dist-info/entry_points.txt
cis_bench-0.5.0.dist-info/top_level.txt
cis_bench-0.5.0.dist-info/RECORD
