Metadata-Version: 2.4
Name: cis-bench
Version: 0.5.0
Summary: CLI tool for fetching and managing CIS benchmarks from CIS WorkBench
Author-email: MITRE SAF Team <saf@mitre.org>
License: Apache-2.0
Project-URL: Homepage, https://github.com/mitre/cis-bench
Project-URL: Documentation, https://mitre.github.io/cis-bench
Project-URL: Repository, https://github.com/mitre/cis-bench
Project-URL: Issues, https://github.com/mitre/cis-bench/issues
Keywords: cis,benchmark,security,compliance,xccdf,scap,nist,mitre
Classifier: Development Status :: 5 - Production/Stable
Classifier: Intended Audience :: Information Technology
Classifier: Intended Audience :: System Administrators
Classifier: License :: OSI Approved :: Apache Software License
Classifier: Programming Language :: Python :: 3
Classifier: Programming Language :: Python :: 3.12
Classifier: Programming Language :: Python :: 3.13
Classifier: Topic :: Security
Classifier: Topic :: System :: Systems Administration
Classifier: Topic :: Utilities
Requires-Python: >=3.12
License-File: LICENSE.md
License-File: NOTICE.md
Requires-Dist: requests>=2.31.0
Requires-Dist: beautifulsoup4>=4.12.2
Requires-Dist: urllib3>=2.0.6
Requires-Dist: pydantic>=2.0.0
Requires-Dist: sqlmodel>=0.0.16
Requires-Dist: alembic>=1.13.0
Requires-Dist: click>=8.1.0
Requires-Dist: rich>=13.7.0
Requires-Dist: questionary>=2.0.0
Requires-Dist: browser-cookie3>=0.19.0
Requires-Dist: truststore>=0.8.0
Requires-Dist: python-dotenv>=1.0.0
Requires-Dist: PyYAML>=6.0.0
Requires-Dist: xsdata[cli,lxml]>=24.0.0
Requires-Dist: lxml>=5.0.0
Provides-Extra: dev
Requires-Dist: pytest>=7.4.0; extra == "dev"
Requires-Dist: pytest-mock>=3.12.0; extra == "dev"
Requires-Dist: pytest-cov>=4.1.0; extra == "dev"
Requires-Dist: ruff>=0.8.0; extra == "dev"
Requires-Dist: bandit[toml]>=1.7.0; extra == "dev"
Requires-Dist: mypy>=1.0.0; extra == "dev"
Requires-Dist: types-requests>=2.31.0; extra == "dev"
Requires-Dist: types-PyYAML>=6.0.0; extra == "dev"
Requires-Dist: pre-commit>=4.0.0; extra == "dev"
Requires-Dist: build>=1.0.0; extra == "dev"
Requires-Dist: twine>=5.0.0; extra == "dev"
Requires-Dist: mkdocs-material>=9.5.0; extra == "dev"
Dynamic: license-file
